pyjaniml/__init__.py
pyjaniml/__main__.py
pyjaniml/converters.py
pyjaniml/janiml.py
pyjaniml/janiml_schema.py
pyjaniml/utils.py
pyjaniml-1.0.0.dist-info/LICENSE
pyjaniml-1.0.0.dist-info/METADATA
pyjaniml-1.0.0.dist-info/WHEEL
pyjaniml-1.0.0.dist-info/top_level.txt
pyjaniml-1.0.0.dist-info/RECORD
