Metadata-Version: 2.1
Name: pyjaniml
Version: 1.0.0
Summary: Classes for AniML handling
Home-page: https://gitlab.com/clade-gmbh/pyjaniml
Author: CLADE GmbH
Author-email: info@clade.io
License: MIT
Keywords: AniML,json
Classifier: Development Status :: 5 - Production/Stable
Classifier: License :: OSI Approved :: MIT License
Classifier: Programming Language :: Python :: 3
Classifier: Operating System :: OS Independent
Classifier: Programming Language :: Python
Classifier: Programming Language :: Python :: 3
Classifier: Programming Language :: Python :: 3.8
Classifier: Programming Language :: Python :: 3.9
Classifier: Programming Language :: Python :: 3.10
Requires-Python: >=3.8
License-File: LICENSE
Requires-Dist: marshmallow >=3.0
Provides-Extra: opus
Requires-Dist: brukeropusreader >=1.3.4 ; extra == 'opus'
